{
  "ver": "5.0",
  "tag": "ipblacklist",
  "data": [
    {
      "id": 0,
      "raddr": "218.48.25.35",
      "tmp_field_sel": true,
      "memo": "[KR]XENON RPG"
    },
    {
      "id": 2,
      "raddr": "43.248.185.161",
      "tmp_field_sel": true,
      "memo": "﻿帝王RPG战役服[数据互通]"
    },
    {
      "id": 4,
      "raddr": "43.248.184.77",
      "tmp_field_sel": true,
      "memo": "3S無人永生RPG战役"
    },
    {
      "id": 5,
      "raddr": "222.187.232.63",
      "tmp_field_sel": true,
      "memo": "风花雪月RPG★测试服"
    },
    {
      "id": 24,
      "raddr": "61.160.213.219",
      "tmp_field_sel": true,
      "memo": "﻿暗黑之魂[RPG]#7"
    },
    {
      "id": 32,
      "raddr": "43.156.84.96",
      "tmp_field_sel": true,
      "memo": "﻿【CN】內鬼樂園"
    }
  ]
}